{
  "sessions": {
    "omx-1778827259120-7n7na4": {
      "ordinary_no_progress_guard": {
        "fingerprint": "ordinary|已完成并推送：`37623be add remembered tray close confirmation` 实现内容： - gallery / docs 窗口关闭时弹出确认： - 关闭进程 - 隐藏窗口并驻留 tray - 支持“记住本次选择” - tray 控制状态新增记忆策略： - 每次询问 - 记住关闭进程 - 记住隐藏到托盘 - demo 的 tray 页面补充了关闭策略控制用例。 - docs 补充了对应说明和 snippet。 - `.omx` 工作日志/状态也已纳入提交。 验证记录： - `cargo fmt` - `cargo check -p aura-gallery` - `cargo check -p aura-docs --bin check_snippets` - `cargo test -p aura-tray` - `cargo test -p aura-gallery` - `cargo test -p aura-docs` 备注：推送后 `.omx/state/*` 又出现了运行时 heartbeat 变更，这是 omx 后台状态的实时更新，不影响本次功能提交。",
        "first_seen_at": "2026-05-15T09:00:52.557Z",
        "last_seen_at": "2026-05-15T09:00:52.557Z",
        "repeat_count": 1,
        "last_turn_id": "019e2ad4-f22c-7683-acad-dc6d1f9018b5",
        "last_thread_id": null
      }
    }
  }
}